{
  "favorites": [
    {
      "id": 8514,
      "obdb_id": "b9-beverages-inc-new-york",
      "name": "B9 Beverages Inc",
      "brewery_type": "contract",
      "street": "404 5th Ave # 7.055",
      "address_2": null,
      "address_3": null,
      "city": "New York",
      "state": "New York",
      "county_province": null,
      "postal_code": "10018-2797",
      "country": "United States",
      "longitude": null,
      "latitude": null,
      "phone": null,
      "website_url": null,
      "updated_at": "2018-08-11T00:00:00.000Z",
      "created_at": "2018-07-24T00:00:00.000Z",
      "rating": 4,
      "comment": "Great IPA's"
    },
    {
      "id": 9645,
      "obdb_id": "cerebral-brewing-denver",
      "name": "Cerebral Brewing",
      "brewery_type": "micro",
      "street": "1477 Monroe St",
      "address_2": null,
      "address_3": null,
      "city": "Denver",
      "state": "Colorado",
      "county_province": null,
      "postal_code": "80206-2708",
      "country": "United States",
      "longitude": "-104.9451783",
      "latitude": "39.73968253",
      "phone": "3039277365",
      "website_url": "http://www.cerebralbrewing.com",
      "updated_at": "2018-08-24T00:00:00.000Z",
      "created_at": "2018-07-24T00:00:00.000Z",
      "comment": "Awesome beers "
    },
    {
      "id": 8063,
      "obdb_id": "14er-brewing-company-denver",
      "name": "14er Brewing Company",
      "brewery_type": "proprietor",
      "street": "2801 Walnut St",
      "address_2": null,
      "address_3": null,
      "city": "Denver",
      "state": "Colorado",
      "county_province": null,
      "postal_code": "80205-2235",
      "country": "United States",
      "longitude": "-104.9839636",
      "latitude": "39.7614112",
      "phone": "7207731437",
      "website_url": "http://www.14erBrewing.com",
      "updated_at": "2018-08-24T00:00:00.000Z",
      "created_at": "2018-07-24T00:00:00.000Z",
      "rating": 5
    },
    {
      "id": 8844,
      "obdb_id": "bierstadt-lagerhaus-denver",
      "name": "Bierstadt Lagerhaus",
      "brewery_type": "brewpub",
      "street": "2875 Blake St",
      "address_2": null,
      "address_3": null,
      "city": "Denver",
      "state": "Colorado",
      "county_province": null,
      "postal_code": "80205-2210",
      "country": "United States",
      "longitude": "-104.9838084",
      "latitude": "39.7630094",
      "phone": "7205707824",
      "website_url": "http://www.bierstadtlager.com",
      "updated_at": "2018-08-24T00:00:00.000Z",
      "created_at": "2018-07-24T00:00:00.000Z",
      "rating": 3
    },
    {
      "id": 10611,
      "obdb_id": "fiction-beer-company-denver",
      "name": "Fiction Beer Company",
      "brewery_type": "micro",
      "street": "7101 E Colfax Ave",
      "address_2": null,
      "address_3": null,
      "city": "Denver",
      "state": "Colorado",
      "county_province": null,
      "postal_code": "80220-1805",
      "country": "United States",
      "longitude": "-104.8854207",
      "latitude": "39.7402188",
      "phone": "7204567163",
      "website_url": "http://www.fictionbeer.com",
      "updated_at": "2018-08-24T00:00:00.000Z",
      "created_at": "2018-07-24T00:00:00.000Z",
      "rating": 4
    },
  ],
  "visited": [
    {
      "id": 10128,
      "obdb_id": "denver-beer-co-denver",
      "name": "Denver Beer Co",
      "brewery_type": "micro",
      "street": "1695 Platte St",
      "address_2": null,
      "address_3": null,
      "city": "Denver",
      "state": "Colorado",
      "county_province": null,
      "postal_code": "80202-1123",
      "country": "United States",
      "longitude": "-105.0072502",
      "latitude": "39.7583143",
      "phone": "3034332739",
      "website_url": "http://www.denverbeerco.com",
      "updated_at": "2018-08-24T00:00:00.000Z",
      "created_at": "2018-07-24T00:00:00.000Z",
      "rating": 4
    },
    {
      "id": 11165,
      "obdb_id": "great-divide-brewing-co-denver",
      "name": "Great Divide Brewing Co",
      "brewery_type": "regional",
      "street": "2201 Arapahoe St",
      "address_2": null,
      "address_3": null,
      "city": "Denver",
      "state": "Colorado",
      "county_province": null,
      "postal_code": "80205-2512",
      "country": "United States",
      "longitude": "-104.9885279",
      "latitude": "39.7539229",
      "phone": "3032969460",
      "website_url": "http://www.greatdivide.com",
      "updated_at": "2018-08-24T00:00:00.000Z",
      "created_at": "2018-07-24T00:00:00.000Z",
      "rating": 5
    },
    {
      "id": 10459,
      "obdb_id": "empire-city-beer-company-new-york",
      "name": "Empire City Beer Company",
      "brewery_type": "planning",
      "street": null,
      "address_2": null,
      "address_3": null,
      "city": "New York",
      "state": "New York",
      "county_province": null,
      "postal_code": "10012",
      "country": "United States",
      "longitude": null,
      "latitude": null,
      "phone": "9178040571",
      "website_url": "http://www.hitemhard.com",
      "updated_at": "2018-08-11T00:00:00.000Z",
      "created_at": "2018-07-24T00:00:00.000Z",
      "rating": 3
    },
    {
      "id": 14028,
      "obdb_id": "ruckus-brewing-co-new-york",
      "name": "Ruckus Brewing Co",
      "brewery_type": "contract",
      "street": "261 W 35th St Ste 1002",
      "address_2": null,
      "address_3": null,
      "city": "New York",
      "state": "New York",
      "county_province": null,
      "postal_code": "10001-1902",
      "country": "United States",
      "longitude": null,
      "latitude": null,
      "phone": "6467105098",
      "website_url": "http://www.ruckusbrewing.com",
      "updated_at": "2018-08-11T00:00:00.000Z",
      "created_at": "2018-07-24T00:00:00.000Z",
      "rating": 2
    },
    {
      "id": 8514,
      "obdb_id": "b9-beverages-inc-new-york",
      "name": "B9 Beverages Inc",
      "brewery_type": "contract",
      "street": "404 5th Ave # 7.055",
      "address_2": null,
      "address_3": null,
      "city": "New York",
      "state": "New York",
      "county_province": null,
      "postal_code": "10018-2797",
      "country": "United States",
      "longitude": null,
      "latitude": null,
      "phone": null,
      "website_url": null,
      "updated_at": "2018-08-11T00:00:00.000Z",
      "created_at": "2018-07-24T00:00:00.000Z",
      "rating": 4
    },
    {
      "id": 8245,
      "obdb_id": "aero-craft-brewing-denver",
      "name": "Aero Craft Brewing",
      "brewery_type": "planning",
      "street": null,
      "address_2": null,
      "address_3": null,
      "city": "Denver",
      "state": "Colorado",
      "county_province": null,
      "postal_code": "80212-2199",
      "country": "United States",
      "longitude": "-104.984696",
      "latitude": "39.7391428",
      "phone": "3039185446",
      "website_url": "http://www.aerocraft.beer",
      "updated_at": "2018-08-24T00:00:00.000Z",
      "created_at": "2018-07-24T00:00:00.000Z"
    },
    {
      "id": 11027,
      "obdb_id": "good-river-beer-company-denver",
      "name": "Good River Beer Company",
      "brewery_type": "contract",
      "street": "1790 S Bannock St.",
      "address_2": null,
      "address_3": null,
      "city": "Denver",
      "state": "Colorado",
      "county_province": null,
      "postal_code": "80223",
      "country": "United States",
      "longitude": "-104.9898169",
      "latitude": "39.68421218",
      "phone": "6023697442",
      "website_url": "http://www.grbeerco.com",
      "updated_at": "2018-08-24T00:00:00.000Z",
      "created_at": "2018-07-24T00:00:00.000Z"
    }
  ]
}